mplapi/__init__.py
mplapi/__main__.py
mplapi/config.py
mplapi/event.py
mplapi/mirai.py
mplapi/msg.py
mplapi/plugin.py
mplapi-0.0.3.dist-info/LICENSE.txt
mplapi-0.0.3.dist-info/METADATA
mplapi-0.0.3.dist-info/WHEEL
mplapi-0.0.3.dist-info/top_level.txt
mplapi-0.0.3.dist-info/RECORD
